AUTHOR
LICENSE
MANIFEST.in
README.rst
setup.cfg
setup.py
doc/source/_static/pyfreesurfer.png
doc/source/_static/carousel/aseg.png
doc/source/_static/carousel/edges.png
doc/source/_static/carousel/polar.png
pyFreeSurfer.egg-info/PKG-INFO
pyFreeSurfer.egg-info/SOURCES.txt
pyFreeSurfer.egg-info/dependency_links.txt
pyFreeSurfer.egg-info/requires.txt
pyFreeSurfer.egg-info/top_level.txt
pyfreesurfer/__init__.py
pyfreesurfer/configuration.py
pyfreesurfer/exceptions.py
pyfreesurfer/fmri.py
pyfreesurfer/hcp.py
pyfreesurfer/info.py
pyfreesurfer/wrapper.py
pyfreesurfer/conversions/__init__.py
pyfreesurfer/conversions/surfconvs.py
pyfreesurfer/conversions/volconvs.py
pyfreesurfer/diffusion/__init__.py
pyfreesurfer/diffusion/tracula.py
pyfreesurfer/plots/__init__.py
pyfreesurfer/plots/formatting.py
pyfreesurfer/plots/polar.py
pyfreesurfer/plots/slicer.py
pyfreesurfer/scripts/pyfreesurfer_conversion
pyfreesurfer/scripts/pyfreesurfer_datacheck
pyfreesurfer/scripts/pyfreesurfer_euler
pyfreesurfer/scripts/pyfreesurfer_fmri
pyfreesurfer/scripts/pyfreesurfer_hcp
pyfreesurfer/scripts/pyfreesurfer_localgi
pyfreesurfer/scripts/pyfreesurfer_qualitycheck
pyfreesurfer/scripts/pyfreesurfer_reconall
pyfreesurfer/scripts/pyfreesurfer_reconall_custom_wm_mask
pyfreesurfer/scripts/pyfreesurfer_reconall_longitudinal
pyfreesurfer/scripts/pyfreesurfer_report_reconall
pyfreesurfer/scripts/pyfreesurfer_statcheck
pyfreesurfer/scripts/pyfreesurfer_stats
pyfreesurfer/scripts/pyfreesurfer_textures
pyfreesurfer/scripts/pyfreesurfer_tracall
pyfreesurfer/scripts/pyfreesurfer_tracall_longitudinal
pyfreesurfer/scripts/pyfreesurfer_tracall_stats
pyfreesurfer/segmentation/__init__.py
pyfreesurfer/segmentation/cortical.py
pyfreesurfer/utils/__init__.py
pyfreesurfer/utils/filetools.py
pyfreesurfer/utils/openctm.py
pyfreesurfer/utils/regtools.py
pyfreesurfer/utils/stattools.py
pyfreesurfer/utils/surftools.py