Metadata-Version: 1.1
Name: pyFreeSurfer
Version: 1.2.0
Summary: 
